sio4onnx/__init__.py
sio4onnx/__main__.py
sio4onnx/onnx_input_output_variable_changer.py
sio4onnx-1.0.3.dist-info/licenses/LICENSE
sio4onnx-1.0.3.dist-info/METADATA
sio4onnx-1.0.3.dist-info/WHEEL
sio4onnx-1.0.3.dist-info/entry_points.txt
sio4onnx-1.0.3.dist-info/top_level.txt
sio4onnx-1.0.3.dist-info/RECORD
